wow_tools/__about__.py
wow_tools/__init__.py
wow_tools/map_creator.py
wow_tools/commands/__init__.py
wow_tools/commands/convert_to_glb.py
wow_tools/commands/convert_to_gltf.py
wow_tools/commands/create_map.py
wow_tools/data/__init__.py
wow_tools/data/map.py
wow_tools/data/model_placement.py
wow_tools/data/vector3.py
wow_tools/data/vector4.py
wow_tools/utils/__init__.py
wow_tools/utils/logging_config.py
wow_tools/utils/model_placement_parser.py
manmade2_wowtools-1.0.2.dist-info/METADATA
manmade2_wowtools-1.0.2.dist-info/WHEEL
manmade2_wowtools-1.0.2.dist-info/licenses/LICENSE.txt
manmade2_wowtools-1.0.2.dist-info/RECORD
